{
    "_lib":"libbpmath.so",
    "_func":{
        "add_int":{
            "_input":[
                "bpbase.BpIntPair"
            ],
            "_output":[
                "bpbase.BpInt"
            ]
        },
        "sub_int":{
            "_input":[
                "bpbase.BpIntPair"
            ],
            "_output":[
                "bpbase.BpInt"
            ]
        },
        "sin_float":{
            "_input":[
                "bpbase.BpFloat"
            ],
            "_output":[
                "bpbase.BpFloat"
            ]
        },
        "add_float":{
            "_input":[
                "bpbase.BpFloat",
                "bpbase.BpFloat"
            ],
            "_output":[
                "bpbase.BpFloat"
            ]
        }
    }
}